{
  "docVersion": "1.0.0",
  "resource": {
    "name": "API Workflow",
    "kind": "package",
    "apiVersion": "orchestrator.uipath.com/v1",
    "projectKey": "68f5a1b9-84e2-4515-a267-64b93673b61c",
    "isOverridable": true,
    "dependencies": [],
    "runtimeDependencies": [],
    "files": [],
    "folders": [
      {
        "fullyQualifiedName": "solution_folder"
      }
    ],
    "spec": {
      "name": "API Workflow"
    },
    "locks": [],
    "key": "ba656273-bd59-4c7d-a1b6-c5ef3122324a"
  }
}